funpy/__init__.py
funpy/fn.py
funpy/io.py
funpy/it.py
funpy/op.py
funpy/pp.py
funpy-0.6.0.dist-info/LICENSE.txt
funpy-0.6.0.dist-info/METADATA
funpy-0.6.0.dist-info/WHEEL
funpy-0.6.0.dist-info/top_level.txt
funpy-0.6.0.dist-info/RECORD
